CYB600_LAB1/__init__.py
CYB600_LAB1/main.py
CYB600_LAB1_M-1.0.4.dist-info/LICENSE
CYB600_LAB1_M-1.0.4.dist-info/METADATA
CYB600_LAB1_M-1.0.4.dist-info/WHEEL
CYB600_LAB1_M-1.0.4.dist-info/entry_points.txt
CYB600_LAB1_M-1.0.4.dist-info/top_level.txt
CYB600_LAB1_M-1.0.4.dist-info/RECORD
